skyplot/__init__.py
skyplot/skyplot.py
skyplot-0.0.1.dist-info/METADATA
skyplot-0.0.1.dist-info/WHEEL
skyplot-0.0.1.dist-info/top_level.txt
skyplot-0.0.1.dist-info/RECORD
