Metadata-Version: 2.1
Name: skyplot
Version: 0.0.1
Summary: Plot sky maps.
Home-page: https://github.com/kjnapes/skyplot
Author: Kevin Napier
Author-email: kjnapier@umich.edu
License: UNKNOWN
Platform: UNKNOWN
